scache/__init__.py
scache-1.3.0.dist-info/LICENSE
scache-1.3.0.dist-info/METADATA
scache-1.3.0.dist-info/WHEEL
scache-1.3.0.dist-info/top_level.txt
scache-1.3.0.dist-info/RECORD
