Metadata-Version: 2.1
Name: scache
Version: 1.3.0
Summary: UNKNOWN
Home-page: https://github.com/smeggingsmegger/scache
License: UNKNOWN
Keywords: simple json key value cache
Platform: UNKNOWN
Requires-Dist: setuptools
